README.rst
setup.py
lib/looping/__init__.py
lib/looping/events.py
lib/looping/pyside.py
lib/looping/pyuv.py
lib/looping/util.py
lib/looping/winsocketpair.py
lib/looping.egg-info/PKG-INFO
lib/looping.egg-info/SOURCES.txt
lib/looping.egg-info/dependency_links.txt
lib/looping.egg-info/requires.txt
lib/looping.egg-info/top_level.txt
lib/looping/test/__init__.py
lib/looping/test/test_events.py
lib/looping/test/test_utils.py