Metadata-Version: 1.1
Name: looping
Version: 0.2
Summary: A PEP3156 interface for various event loops
Home-page: https://github.com/geertj/looping
Author: Geert Jansen
Author-email: geertj@gmail.com
License: Apache 2.0
Platform: UNKNOWN
Classifier: Development Status :: 4 - Beta
Classifier: License :: OSI Approved :: Apache Software License
Classifier: Operating System :: POSIX
Classifier: Programming Language :: Python :: 2.6
Classifier: Programming Language :: Python :: 2.7
Classifier: Programming Language :: Python :: 3.2
Classifier: Programming Language :: Python :: 3.3
